Metadata-Version: 2.1
Name: odoo14-addon-l10n-es-aeat-sii-oca
Version: 14.0.2.10.2
Summary: Suministro Inmediato de Información en el IVA
Home-page: https://github.com/OCA/l10n-spain
Author: Acysos S.L.,Diagram,Minorisa,Studio73,FactorLibre,Comunitea,Otherway,Tecnativa,Javi Melendez,Odoo Community Association (OCA)
Author-email: support@odoo-community.org
License: AGPL-3
Platform: UNKNOWN
Classifier: Programming Language :: Python
Classifier: Framework :: Odoo
Classifier: Framework :: Odoo :: 14.0
Classifier: License :: OSI Approved :: GNU Affero General Public License v3
Classifier: Development Status :: 5 - Production/Stable
Requires-Python: >=3.6
Requires-Dist: cryptography <39
Requires-Dist: odoo14-addon-account-invoice-refund-link
Requires-Dist: odoo14-addon-l10n-es-aeat
Requires-Dist: odoo14-addon-queue-job
Requires-Dist: odoo <14.1dev,>=14.0a
Requires-Dist: requests
Requires-Dist: zeep
